OceanColor/OceanColor.py
OceanColor/__init__.py
OceanColor/catalog.py
OceanColor/cli.py
OceanColor/cmr.py
OceanColor/gsfc.py
OceanColor/inrange.py
OceanColor/storage.py
OceanColor/utils.py
OceanColor/version.py
OceanColor/backend/__init__.py
OceanColor/backend/common.py
OceanColor-0.1.0.dist-info/AUTHORS.rst
OceanColor-0.1.0.dist-info/LICENSE
OceanColor-0.1.0.dist-info/METADATA
OceanColor-0.1.0.dist-info/WHEEL
OceanColor-0.1.0.dist-info/entry_points.txt
OceanColor-0.1.0.dist-info/top_level.txt
OceanColor-0.1.0.dist-info/RECORD
