Metadata-Version: 2.1
Name: OceanColor
Version: 0.1.0
Summary: Deal with NASA Ocean Color data (search and download)
Author: Guilherme Castelao
Author-email: guilherme@castelao.net
License: BSD License
Project-URL: homepage, https://github.com/castelao/OceanColor
Project-URL: documentation, https://oceancolor.readthedocs.io
Project-URL: repository, https://github.com/castelao/OceanColor
Keywords: NASA,Ocean Color,chlorophyll,oceanography,matchup
Classifier: Development Status :: 4 - Beta
Classifier: Intended Audience :: Science/Research
Classifier: License :: OSI Approved :: BSD License
Classifier: Natural Language :: English
Classifier: Programming Language :: Python :: 3
Classifier: Programming Language :: Python :: 3.9
Classifier: Programming Language :: Python :: 3.10
Classifier: Programming Language :: Python :: 3.11
Classifier: Topic :: Scientific/Engineering
Requires-Python: >=3.8
License-File: LICENSE
License-File: AUTHORS.rst
Requires-Dist: Click >=8.0
Requires-Dist: numpy >=1.21
Requires-Dist: netCDF4 >=1.5.6
Requires-Dist: pandas >=1.3
Requires-Dist: pyproj >=3.0
Requires-Dist: python-cmr ~=0.9.0
Requires-Dist: requests >=2.27
Requires-Dist: xarray >=0.19
Requires-Dist: fsspec >=2022.1
Requires-Dist: aiohttp >=3.8.1
Provides-Extra: dev
Requires-Dist: black ~=23.9.0 ; extra == 'dev'
Requires-Dist: pyupgrade ~=3.2.2 ; extra == 'dev'
Requires-Dist: pre-commit ~=2.20.0 ; extra == 'dev'
Requires-Dist: sphinx-rtd-theme ~=0.4.3 ; extra == 'dev'
Provides-Extra: parallel
Requires-Dist: dask >=2022.1 ; extra == 'parallel'
Requires-Dist: loky >=2.9 ; extra == 'parallel'
Provides-Extra: s3
Requires-Dist: s3fs >=2022.1 ; extra == 's3'
Requires-Dist: zarr >=2.10 ; extra == 's3'
Provides-Extra: test
Requires-Dist: pytest ; extra == 'test'
Requires-Dist: pytest-cov >=3.0 ; extra == 'test'
